onvifscout/__init__.py
onvifscout/auth.py
onvifscout/discovery.py
onvifscout/features.py
onvifscout/help_formatter.py
onvifscout/main.py
onvifscout/models.py
onvifscout/utils.py
onvifscout-1.0.1.dist-info/LICENSE
onvifscout-1.0.1.dist-info/METADATA
onvifscout-1.0.1.dist-info/WHEEL
onvifscout-1.0.1.dist-info/entry_points.txt
onvifscout-1.0.1.dist-info/top_level.txt
onvifscout-1.0.1.dist-info/RECORD
