Metadata-Version: 2.1
Name: onvifscout
Version: 1.0.1
Summary: A comprehensive ONVIF device discovery and analysis tool for network cameras and devices
Home-page: https://github.com/chrissmartin/onvifscout
Author: Chriss Martin
Author-email: thechrissmartin@gmail.com
Project-URL: Bug Tracker, https://github.com/chrissmartin/onvifscout/issues
Project-URL: Documentation, https://github.com/chrissmartin/onvifscout
Project-URL: Source Code, https://github.com/chrissmartin/onvifscout
Keywords: onvif camera network security monitoring discovery ip-camera cctv surveillance
Classifier: Development Status :: 4 - Beta
Classifier: Intended Audience :: System Administrators
Classifier: Intended Audience :: Developers
Classifier: License :: OSI Approved :: MIT License
Classifier: Operating System :: OS Independent
Classifier: Programming Language :: Python :: 3
Classifier: Programming Language :: Python :: 3.8
Classifier: Programming Language :: Python :: 3.9
Classifier: Programming Language :: Python :: 3.10
Classifier: Programming Language :: Python :: 3.11
Classifier: Topic :: System :: Networking :: Monitoring
Classifier: Topic :: Security
Classifier: Topic :: System :: Systems Administration
Classifier: Topic :: Software Development :: Libraries :: Python Modules
Requires-Python: >=3.8
License-File: LICENSE
Requires-Dist: colorama>=0.4.6
Requires-Dist: requests>=2.32.3
